build/lib/phenotools/__init__.py
build/lib/phenotools/__main__.py
build/lib/phenotools/config.ini
build/lib/phenotools/db.sqlite3
build/lib/phenotools/version.json
build/lib/phenotools/backend/__init__.py
build/lib/phenotools/backend/asgi.py
build/lib/phenotools/backend/settings.py
build/lib/phenotools/backend/urls.py
build/lib/phenotools/backend/wsgi.py
build/lib/phenotools/common/__init__.py
build/lib/phenotools/common/config_parser.py
build/lib/phenotools/common/customexception.py
build/lib/phenotools/common/custommodelviewset.py
build/lib/phenotools/common/customresponse.py
build/lib/phenotools/dataset/__init__.py
build/lib/phenotools/dataset/admin.py
build/lib/phenotools/dataset/apps.py
build/lib/phenotools/dataset/models.py
build/lib/phenotools/dataset/serializers.py
build/lib/phenotools/dataset/tests.py
build/lib/phenotools/dataset/urls.py
build/lib/phenotools/dataset/views.py
build/lib/phenotools/file/__init__.py
build/lib/phenotools/file/admin.py
build/lib/phenotools/file/apps.py
build/lib/phenotools/file/serializers.py
build/lib/phenotools/file/tests.py
build/lib/phenotools/file/urls.py
build/lib/phenotools/file/views.py
build/lib/phenotools/logs/__init__.py
build/lib/phenotools/logs/shutdown.log
build/lib/phenotools/logs/web/system.log
build/lib/phenotools/model/__init__.py
build/lib/phenotools/model/admin.py
build/lib/phenotools/model/apps.py
build/lib/phenotools/model/models.py
build/lib/phenotools/model/serializers.py
build/lib/phenotools/model/tests.py
build/lib/phenotools/model/urls.py
build/lib/phenotools/model/views.py
build/lib/phenotools/modules/__init__.py
build/lib/phenotools/modules/predict.py
build/lib/phenotools/modules/train.py
build/lib/phenotools/modules/utils.py
build/lib/phenotools/modules/basic/__init__.py
build/lib/phenotools/modules/basic/main.py
build/lib/phenotools/modules/basic/test.py
build/lib/phenotools/modules/basic/train.py
build/lib/phenotools/modules/basic/version.py
build/lib/phenotools/modules/basic/archs/__init__.py
phenotools-1.0.1.dist-info/LICENSE.txt
phenotools-1.0.1.dist-info/METADATA
phenotools-1.0.1.dist-info/WHEEL
phenotools-1.0.1.dist-info/entry_points.txt
phenotools-1.0.1.dist-info/top_level.txt
phenotools-1.0.1.dist-info/RECORD
